subscraper
