Metadata-Version: 1.0
Name: subscraper
Version: 0.4
Summary: Movies/Series Subtitle Downloader
Home-page: http://github.com/charmpitz/subscraper
Author: Andrei Pit
Author-email: charmpitz@gmail.com
License: MIT
Platform: UNKNOWN
